<?xml version="1.0" encoding="UTF-8" standalone="no"?>
<!DOCTYPE properties SYSTEM "http://java.sun.com/dtd/properties.dtd">
<properties>
    <comment/>
    <entry key="xsdFile">..\XMLParser\src\main\resources\Gems.xsd</entry>
    <entry key="xslFile">..\XMLParser\src\main\resources\TransformGems.xsl</entry>
    <entry key="originalFile">..\XMLParser\src\main\resources\Gems_test3.xml</entry>
    <entry key="changeJAXBFile">..\XMLParser\Gems_changeJAXB.xml</entry>
    <entry key="changeDOMFile">..\XMLParser\Gems_changeDOM.xml</entry>
    <entry key="changeStAXFile">..\XMLParser\Gems_changeStAX.xml</entry>
    <entry key="transformFile">..\XMLParser\changeByXSLTransform.xml</entry>
</properties>
